main.py
organizer_cli-0.1.0.dist-info/LICENSE
organizer_cli-0.1.0.dist-info/METADATA
organizer_cli-0.1.0.dist-info/WHEEL
organizer_cli-0.1.0.dist-info/entry_points.txt
organizer_cli-0.1.0.dist-info/top_level.txt
organizer_cli-0.1.0.dist-info/RECORD
