Metadata-Version: 2.1
Name: organizer-cli
Version: 0.1.0
Summary: A Python CLI tool that goes through a given directory and organizes all un-folder bound files into folders by file extension.
Home-page: https://github.com/Mulaza/File-Organizer
Author: Mulaza Jacinto
Author-email: mulazajacinto@Gmail.com
License: UNKNOWN
Platform: UNKNOWN
Classifier: Development Status :: 4 - Beta
Classifier: Intended Audience :: End Users/Desktop
Classifier: Natural Language :: English
Classifier: Programming Language :: Python :: 3.7
Classifier: Programming Language :: Python :: 3.8
Requires-Dist: Click
Requires-Dist: colorama
Requires-Dist: progress
